nteu_corporate_engine/__init__.py
nteu_corporate_engine/engine.py
nteu_corporate_engine/pipeline.py
nteu_corporate_engine/server.py
nteu_corporate_engine-0.1.65.dist-info/WHEEL
nteu_corporate_engine-0.1.65.dist-info/METADATA
nteu_corporate_engine-0.1.65.dist-info/RECORD
