Metadata-Version: 2.1
Name: nteu-corporate-engine
Version: 0.1.65
Summary: NTEU model wrapper for corporate injection
Author: Your Name
Author-email: you@example.com
Requires-Python: >=3.7,<4.0
Classifier: Programming Language :: Python :: 3
Classifier: Programming Language :: Python :: 3.7
Classifier: Programming Language :: Python :: 3.8
Classifier: Programming Language :: Python :: 3.9
Classifier: Programming Language :: Python :: 3.10
Classifier: Programming Language :: Python :: 3.11
Requires-Dist: OpenNMT-py (==1.1.0)
Requires-Dist: aiohttp (>=3.6.3,<4.0.0)
Requires-Dist: pangeamt-nlp (>=1.0.0,<2.0.0)
Requires-Dist: pangeamt-toolkit (>=3.57.0,<4.0.0)
Requires-Dist: prettytable (>=1.0.1,<2.0.0)
Requires-Dist: torch (==1.5.0)
